alt_eval/__init__.py
alt_eval/error_visualizer.py
alt_eval/metrics.py
alt_eval/normalization.py
alt_eval/tokenizer.py
alt_eval-1.2.0.dist-info/LICENSE
alt_eval-1.2.0.dist-info/METADATA
alt_eval-1.2.0.dist-info/WHEEL
alt_eval-1.2.0.dist-info/top_level.txt
alt_eval-1.2.0.dist-info/RECORD
