Metadata-Version: 2.1
Name: alt-eval
Version: 1.2.0
Summary: Automatic lyrics transcription evaluation toolkit
Author: Ondřej Cífka
Classifier: License :: OSI Approved :: MIT License
Classifier: Programming Language :: Python :: 3 :: Only
Classifier: Programming Language :: Python :: 3.9
Classifier: Programming Language :: Python :: 3.10
Classifier: Programming Language :: Python :: 3.11
Classifier: Programming Language :: Python :: 3.12
Classifier: Programming Language :: Python :: 3.13
Classifier: Topic :: Multimedia :: Sound/Audio
Classifier: Topic :: Multimedia :: Sound/Audio :: Speech
Classifier: Topic :: Scientific/Engineering :: Artificial Intelligence
Requires-Python: >=3.9
License-File: LICENSE
Requires-Dist: jiwer >=3.0.3
Requires-Dist: python-iso639 >=2023.6.15
Requires-Dist: regex >=2023.8.8
Requires-Dist: sacremoses ==0.0.53
Provides-Extra: dev
Requires-Dist: pre-commit ==3.7.1 ; extra == 'dev'
Provides-Extra: test
Requires-Dist: pytest >=7.3.1 ; extra == 'test'
